Metadata-Version: 2.1
Name: memcalc
Version: 0.0.1
Summary: calculator with essential math functions
Home-page: UNKNOWN
Author: David Balsys
Author-email: davidbalsys@gmail.com
License: MIT
Keywords: calculator
Platform: UNKNOWN
License-File: LICENSE.txt
